seeqlite/__init__.py
seeqlite/main.py
seeqlite-0.1.2.dist-info/licenses/LICENCE
seeqlite-0.1.2.dist-info/METADATA
seeqlite-0.1.2.dist-info/WHEEL
seeqlite-0.1.2.dist-info/entry_points.txt
seeqlite-0.1.2.dist-info/top_level.txt
seeqlite-0.1.2.dist-info/RECORD
