Metadata-Version: 2.4
Name: seeqlite
Version: 0.1.2
Summary: A simple and interactive terminal viewer for SQLite databases.
Author-email: Daniel Bergmann <61001914+daniel-bergmann@users.noreply.github.com>
Classifier: Programming Language :: Python :: 3
Classifier: Operating System :: OS Independent
Classifier: Topic :: Database
Classifier: Environment :: Console
Requires-Python: >=3.7
License-File: LICENCE
Dynamic: license-file
